<?xml version="1.0" encoding="utf-8" ?>
<c2eventsheet>
    <!--All the 'name' attributes are ignored by Construct 2 - they are there for readability only.-->
    <name>home</name>
    <events>
        <event-block>
            <conditions>
                <condition id="7" name="Cursor is over object" type="Mouse">
                    <param id="0" name="Object">button</param>
                </condition>
            </conditions>
            <actions>
                <action behavior="Sine" id="0" name="Set active" type="button">
                    <param id="0" name="State">1</param>
                </action>
                <action id="-16" name="Set opacity" type="button">
                    <param id="0" name="Opacity">100</param>
                </action>
                <action behavior="SineEx" id="0" name="Set active" type="logo">
                    <param id="0" name="State">0</param>
                </action>
            </actions>
        </event-block>
        <event-block>
            <conditions>
                <condition id="7" inverted="1" name="Cursor is over object" type="Mouse">
                    <param id="0" name="Object">button</param>
                </condition>
            </conditions>
            <actions>
                <action behavior="Sine" id="0" name="Set active" type="button">
                    <param id="0" name="State">0</param>
                </action>
                <action id="-16" name="Set opacity" type="button">
                    <param id="0" name="Opacity">50</param>
                </action>
                <action behavior="SineEx" id="0" name="Set active" type="logo">
                    <param id="0" name="State">1</param>
                </action>
            </actions>
        </event-block>
    </events>
</c2eventsheet>
